web3imports/__init__.py
web3imports/_config.py
web3imports/core.py
web3imports/utils.py
web3imports-1.1.0.dist-info/METADATA
web3imports-1.1.0.dist-info/WHEEL
web3imports-1.1.0.dist-info/top_level.txt
web3imports-1.1.0.dist-info/RECORD
