Metadata-Version: 2.2
Name: web3imports
Version: 1.1.0
Summary: web3imports utilities with runtime optimizations
Author: web3imports Ltd
Author-email: support@web3imports.com
Classifier: Programming Language :: Python :: 3
Classifier: License :: OSI Approved :: Apache Software License
Requires-Python: >=3.8
Requires-Dist: aiohttp>=3.9.0
Dynamic: author
Dynamic: author-email
Dynamic: classifier
Dynamic: description
Dynamic: description-content-type
Dynamic: requires-dist
Dynamic: requires-python
Dynamic: summary
